{
  "projects": [
    {
      "name": "Teste 1asasas",
      "budget": "1000",
      "category": {
        "id": "2",
        "name": "Desenvolvimento"
      },
      "cost": 200,
      "services": [
        {
          "name": "teste serviço 1",
          "cost": "200",
          "description": "Testando a exibição do card service",
          "id": "3fcdec23-536f-40bf-8e2e-b246f5c25fe2"
        }
      ],
      "id": 1
    },
    {
      "name": "Teste 2",
      "budget": "50000",
      "category": {
        "id": "3",
        "name": "Design"
      },
      "cost": 0,
      "services": [],
      "id": 2
    },
    {
      "name": "Teste da quinta",
      "budget": "1000",
      "category": {
        "id": "3",
        "name": "Design"
      },
      "cost": 0,
      "services": [],
      "id": 3
    }
  ],
  "categories": [
    {
      "id": 1,
      "name": "Infra"
    },
    {
      "id": 2,
      "name": "Desenvolvimento"
    },
    {
      "id": 3,
      "name": "Design"
    },
    {
      "id": 4,
      "name": "Planejamento"
    }
  ]
}